CHANGES.txt
COPYRIGHT.txt
LICENSE.txt
README.txt
bootstrap.py
buildout.cfg
setup.py
src/nt_svcutils/__init__.py
src/nt_svcutils/service.py
src/nt_svcutils.egg-info/PKG-INFO
src/nt_svcutils.egg-info/SOURCES.txt
src/nt_svcutils.egg-info/dependency_links.txt
src/nt_svcutils.egg-info/not-zip-safe
src/nt_svcutils.egg-info/top_level.txt