Metadata-Version: 1.0
Name: nt-svcutils
Version: 2.13.0
Summary: nt_svcutils for Zope2.
Home-page: http://pypi.python.org/pypi/nt_svcutils
Author: Zope Foundation and Contributors
Author-email: zope-dev@zope.org
License: ZPL 2.1
Platform: UNKNOWN
